{
  "$schema": "https://developer.microsoft.com/json-schemas/fabric/item/report/definition/visualContainer/2.10.0/schema.json",
  "name": "1b27096ace7db50e6f14",
  "position": {
    "x": 989.49518093293148,
    "y": 652.86279979080018,
    "z": 5000,
    "height": 46.92451373496376,
    "width": 289.70786740716756,
    "tabOrder": 5000
  },
  "visual": {
    "visualType": "textbox",
    "objects": {
      "general": [
        {
          "properties": {
            "paragraphs": [
              {
                "textRuns": [
                  {
                    "value": "organic revenue is excluded.",
                    "textStyle": {
                      "fontSize": "16pt"
                    }
                  }
                ]
              }
            ]
          }
        }
      ]
    },
    "drillFilterOtherVisuals": true
  }
}